api/__init__.py
api/commons.py
api/hydrometry.py
api/rest_client.py
api/models/__init__.py
api/models/station_hydrometrique.py
hubeau_api_client-0.0.3.dist-info/LICENSE
hubeau_api_client-0.0.3.dist-info/METADATA
hubeau_api_client-0.0.3.dist-info/WHEEL
hubeau_api_client-0.0.3.dist-info/top_level.txt
hubeau_api_client-0.0.3.dist-info/RECORD
