Metadata-Version: 2.1
Name: hubeau-api-client
Version: 0.0.3
Summary: Hubeau Rest API Client
Home-page: https://github.com/lrk/hubeau-api-client
Author: Lrk
Author-email: sfxelrick@gmail.com
License: UNKNOWN
Project-URL: Bug Reports, https://github.com/lrk/hubeau-api-client/issues
Project-URL: Source, https://github.com/lrk/hubeau-api-client
Keywords: hubeau,api,rest
Platform: UNKNOWN
Classifier: Development Status :: 3 - Alpha
Classifier: License :: OSI Approved :: Apache Software License
Classifier: Programming Language :: Python :: 3
Classifier: Natural Language :: French
Classifier: Intended Audience :: Developers
Classifier: Topic :: Software Development :: Build Tools
Requires-Dist: requests
Provides-Extra: dev
Requires-Dist: check-manifest ; extra == 'dev'
Provides-Extra: test
Requires-Dist: coverage ; extra == 'test'
